{
  "contract": "../data/dataset/bsc2/0x240222f0B8a394a08065A102b13604Fe162A953c.hex",
  "tool": "maian",
  "start": 1659481691.991341,
  "end": 1659481697.518552,
  "exit_code": 0,
  "duration": 5.52721095085144,
  "success": false,
  "findings": [
    "Accepts_Ether",
    "Ether_lock_Ether_accepted_without_send",
    "No_Ether_leak_no_send",
    "Not_destructible_no_self_destruct"
  ],
  "errors": [
    "Unknown operation"
  ],
  "analysis": [
    {
      "file": "",
      "contract": "",
      "findings": [
        "Accepts Ether",
        "Ether lock (Ether accepted without send)",
        "No Ether leak (no send)",
        "Not destructible (no self-destruct)"
      ],
      "errors": [
        "Unknown operation"
      ]
    }
  ]
}