{
  "contract": "../data/dataset/bsc2/0xe4c0602f5dcfe59310805C18484e79c6FF84f909.hex",
  "tool": "securify",
  "start": 1659498172.7294266,
  "end": 1659498176.33018,
  "exit_code": 0,
  "duration": 3.6007533073425293,
  "success": true,
  "findings": [],
  "errors": [],
  "analysis": {
    "../data/dataset/bsc2/0xe4c0602f5dcfe59310805C18484e79c6FF84f909.hex:0xe4c0602f5dcfe59310805C18484e79c6FF84f909": {
      "results": {
        "DAO": {
          "completed": true,
          "hasViolations": false,
          "hasWarnings": false,
          "hasSafe": false,
          "hasConflicts": false,
          "violations": [],
          "warnings": [],
          "safe": [],
          "conflicts": []
        },
        "DAOConstantGas": {
          "completed": true,
          "hasViolations": false,
          "hasWarnings": false,
          "hasSafe": false,
          "hasConflicts": false,
          "violations": [],
          "warnings": [],
          "safe": [],
          "conflicts": []
        },
        "MissingInputValidation": {
          "completed": true,
          "error": "not supported",
          "hasViolations": false,
          "hasWarnings": false,
          "hasSafe": false,
          "hasConflicts": false,
          "violations": [],
          "warnings": [],
          "safe": [],
          "conflicts": []
        },
        "TODAmount": {
          "completed": true,
          "hasViolations": false,
          "hasWarnings": false,
          "hasSafe": false,
          "hasConflicts": false,
          "violations": [],
          "warnings": [],
          "safe": [],
          "conflicts": []
        },
        "TODReceiver": {
          "completed": true,
          "hasViolations": false,
          "hasWarnings": false,
          "hasSafe": false,
          "hasConflicts": false,
          "violations": [],
          "warnings": [],
          "safe": [],
          "conflicts": []
        },
        "TODTransfer": {
          "completed": true,
          "hasViolations": false,
          "hasWarnings": false,
          "hasSafe": false,
          "hasConflicts": false,
          "violations": [],
          "warnings": [],
          "safe": [],
          "conflicts": []
        },
        "UnhandledException": {
          "completed": true,
          "hasViolations": false,
          "hasWarnings": false,
          "hasSafe": false,
          "hasConflicts": false,
          "violations": [],
          "warnings": [],
          "safe": [],
          "conflicts": []
        },
        "UnrestrictedEtherFlow": {
          "completed": true,
          "hasViolations": false,
          "hasWarnings": false,
          "hasSafe": false,
          "hasConflicts": false,
          "violations": [],
          "warnings": [],
          "safe": [],
          "conflicts": []
        }
      }
    }
  }
}