{
  "contract": "../data/dataset/eth2/0x8a8634df47aeeD047eeBE3FcCaF5e62B3B342E14.hex",
  "tool": "securify",
  "start": 1659402783.041964,
  "end": 1659402785.8499875,
  "exit_code": 0,
  "duration": 2.808023452758789,
  "success": true,
  "findings": [],
  "errors": [],
  "analysis": {
    "../data/dataset/eth2/0x8a8634df47aeeD047eeBE3FcCaF5e62B3B342E14.hex:0x8a8634df47aeeD047eeBE3FcCaF5e62B3B342E14": {
      "results": {
        "DAO": {
          "completed": true,
          "hasViolations": false,
          "hasWarnings": false,
          "hasSafe": false,
          "hasConflicts": false,
          "violations": [],
          "warnings": [],
          "safe": [],
          "conflicts": []
        },
        "DAOConstantGas": {
          "completed": true,
          "hasViolations": false,
          "hasWarnings": false,
          "hasSafe": false,
          "hasConflicts": false,
          "violations": [],
          "warnings": [],
          "safe": [],
          "conflicts": []
        },
        "MissingInputValidation": {
          "completed": true,
          "error": "not supported",
          "hasViolations": false,
          "hasWarnings": false,
          "hasSafe": false,
          "hasConflicts": false,
          "violations": [],
          "warnings": [],
          "safe": [],
          "conflicts": []
        },
        "TODAmount": {
          "completed": true,
          "hasViolations": false,
          "hasWarnings": false,
          "hasSafe": false,
          "hasConflicts": false,
          "violations": [],
          "warnings": [],
          "safe": [],
          "conflicts": []
        },
        "TODReceiver": {
          "completed": true,
          "hasViolations": false,
          "hasWarnings": false,
          "hasSafe": false,
          "hasConflicts": false,
          "violations": [],
          "warnings": [],
          "safe": [],
          "conflicts": []
        },
        "TODTransfer": {
          "completed": true,
          "hasViolations": false,
          "hasWarnings": false,
          "hasSafe": false,
          "hasConflicts": false,
          "violations": [],
          "warnings": [],
          "safe": [],
          "conflicts": []
        },
        "UnhandledException": {
          "completed": true,
          "hasViolations": false,
          "hasWarnings": false,
          "hasSafe": false,
          "hasConflicts": false,
          "violations": [],
          "warnings": [],
          "safe": [],
          "conflicts": []
        },
        "UnrestrictedEtherFlow": {
          "completed": true,
          "hasViolations": false,
          "hasWarnings": false,
          "hasSafe": false,
          "hasConflicts": false,
          "violations": [],
          "warnings": [],
          "safe": [],
          "conflicts": []
        }
      }
    }
  }
}