{
  "contract": "../data/dataset/bsc/0xe8928F00e7BD5691e13CeF9A0D3d619947566Fd1.hex",
  "tool": "securify",
  "start": 1657562796.599114,
  "end": 1657562800.2315378,
  "exit_code": 0,
  "duration": 3.6324238777160645,
  "success": true,
  "findings": [],
  "errors": [],
  "analysis": {
    "../data/dataset/bsc/0xe8928F00e7BD5691e13CeF9A0D3d619947566Fd1.hex:0xe8928F00e7BD5691e13CeF9A0D3d619947566Fd1": {
      "results": {
        "DAO": {
          "completed": true,
          "hasViolations": false,
          "hasWarnings": false,
          "hasSafe": false,
          "hasConflicts": false,
          "violations": [],
          "warnings": [],
          "safe": [],
          "conflicts": []
        },
        "DAOConstantGas": {
          "completed": true,
          "hasViolations": false,
          "hasWarnings": false,
          "hasSafe": false,
          "hasConflicts": false,
          "violations": [],
          "warnings": [],
          "safe": [],
          "conflicts": []
        },
        "MissingInputValidation": {
          "completed": true,
          "error": "not supported",
          "hasViolations": false,
          "hasWarnings": false,
          "hasSafe": false,
          "hasConflicts": false,
          "violations": [],
          "warnings": [],
          "safe": [],
          "conflicts": []
        },
        "TODAmount": {
          "completed": true,
          "hasViolations": false,
          "hasWarnings": false,
          "hasSafe": false,
          "hasConflicts": false,
          "violations": [],
          "warnings": [],
          "safe": [],
          "conflicts": []
        },
        "TODReceiver": {
          "completed": true,
          "hasViolations": false,
          "hasWarnings": false,
          "hasSafe": false,
          "hasConflicts": false,
          "violations": [],
          "warnings": [],
          "safe": [],
          "conflicts": []
        },
        "TODTransfer": {
          "completed": true,
          "hasViolations": false,
          "hasWarnings": false,
          "hasSafe": false,
          "hasConflicts": false,
          "violations": [],
          "warnings": [],
          "safe": [],
          "conflicts": []
        },
        "UnhandledException": {
          "completed": true,
          "hasViolations": false,
          "hasWarnings": false,
          "hasSafe": false,
          "hasConflicts": false,
          "violations": [],
          "warnings": [],
          "safe": [],
          "conflicts": []
        },
        "UnrestrictedEtherFlow": {
          "completed": true,
          "hasViolations": false,
          "hasWarnings": false,
          "hasSafe": false,
          "hasConflicts": false,
          "violations": [],
          "warnings": [],
          "safe": [],
          "conflicts": []
        }
      }
    }
  }
}