{
  "contract": "../data/dataset/eth2/0x47F35E35f6323101dFd3ba906492B42ce97d6409.hex",
  "tool": "securify",
  "start": 1659416061.0335364,
  "end": 1659416066.1787472,
  "exit_code": 0,
  "duration": 5.1452107429504395,
  "success": true,
  "findings": [],
  "errors": [],
  "analysis": {
    "../data/dataset/eth2/0x47F35E35f6323101dFd3ba906492B42ce97d6409.hex:0x47F35E35f6323101dFd3ba906492B42ce97d6409": {
      "results": {
        "DAO": {
          "completed": true,
          "hasViolations": false,
          "hasWarnings": false,
          "hasSafe": false,
          "hasConflicts": false,
          "violations": [],
          "warnings": [],
          "safe": [],
          "conflicts": []
        },
        "DAOConstantGas": {
          "completed": true,
          "hasViolations": false,
          "hasWarnings": false,
          "hasSafe": false,
          "hasConflicts": false,
          "violations": [],
          "warnings": [],
          "safe": [],
          "conflicts": []
        },
        "MissingInputValidation": {
          "completed": true,
          "error": "not supported",
          "hasViolations": false,
          "hasWarnings": false,
          "hasSafe": false,
          "hasConflicts": false,
          "violations": [],
          "warnings": [],
          "safe": [],
          "conflicts": []
        },
        "TODAmount": {
          "completed": true,
          "hasViolations": false,
          "hasWarnings": false,
          "hasSafe": false,
          "hasConflicts": false,
          "violations": [],
          "warnings": [],
          "safe": [],
          "conflicts": []
        },
        "TODReceiver": {
          "completed": true,
          "hasViolations": false,
          "hasWarnings": false,
          "hasSafe": false,
          "hasConflicts": false,
          "violations": [],
          "warnings": [],
          "safe": [],
          "conflicts": []
        },
        "TODTransfer": {
          "completed": true,
          "hasViolations": false,
          "hasWarnings": false,
          "hasSafe": false,
          "hasConflicts": false,
          "violations": [],
          "warnings": [],
          "safe": [],
          "conflicts": []
        },
        "UnhandledException": {
          "completed": true,
          "hasViolations": false,
          "hasWarnings": false,
          "hasSafe": false,
          "hasConflicts": false,
          "violations": [],
          "warnings": [],
          "safe": [],
          "conflicts": []
        },
        "UnrestrictedEtherFlow": {
          "completed": true,
          "hasViolations": false,
          "hasWarnings": false,
          "hasSafe": false,
          "hasConflicts": false,
          "violations": [],
          "warnings": [],
          "safe": [],
          "conflicts": []
        }
      }
    }
  }
}