{
  "contract": "../data/dataset/bsc/0xB794aA7385Abd9e9fEdC047552B9e378801400E9.hex",
  "tool": "honeybadger",
  "start": 1657532875.694955,
  "end": 1657532877.939471,
  "exit_code": 0,
  "duration": 2.244515895843506,
  "success": false,
  "findings": [],
  "errors": [
    "instruction error"
  ],
  "analysis": [
    {
      "EVM code coverage": "2.4%",
      "Money flow": false,
      "Balance disorder": false,
      "Hidden transfer": false,
      "Inheritance disorder": false,
      "Uninitialised struct": false,
      "Type overflow": false,
      "Skip empty string": false,
      "Hidden state update": false,
      "Straw man contract": false
    }
  ]
}