{
  "contract": "../data/dataset/eth2/0x458FCD33AD32DE55875578da8cF1248B8765EC95.hex",
  "tool": "madmax",
  "start": 1659404673.376189,
  "end": 1659404678.4488406,
  "exit_code": 0,
  "duration": 5.072651624679565,
  "success": true,
  "findings": [],
  "errors": [],
  "analysis": [
    [
      "0x458FCD33AD32DE55875578da8cF1248B8765EC95.hex",
      [
        "TAC_Def",
        "VulnerabilityDescription_UnboundedMassOp",
        "Mask_Length",
        "TAC_Block",
        "LoadFromDataStructure",
        "inliner",
        "UnmappedStatements",
        "Analytics_MemConsStmtUsesFromDistinctPaths",
        "Analytics_FunctionCall",
        "TAC_OriginalStatement_Block",
        "MemWriteToMemConsStmtUpperLimit",
        "HasStorageOpsUnknown",
        "FormalArgs",
        "Analytics_PublicFunction",
        "Analytics_Jumps",
        "inliner",
        "ConstWrittenToBytesOfStorVar",
        "inliner",
        "Analytics_CallWithSig",
        "OpcodePossiblyHalts",
        "Analytics_PublicFunctionArrayArg",
        "MemWriteToMemConsStmtPartOfPrev",
        "inliner",
        "TAC_Variable_BlockValue",
        "IRFunction_Return",
        "inliner",
        "inliner",
        "StatementUsesMemoryOfNonComputableLength_LengthApprox",
        "MSTOREToMemConsStmtWritesShiftedVar",
        "TAC_Variable_Value",
        "IsKnownStore",
        "MemoryStatement_ActualArgNew",
        "IRFallthroughEdge",
        "Analytics_FunctionWithMultipleReturns",
        "VarWrittenToBytesOfStorVar",
        "Analytics_NonModeledMSTORE",
        "LShiftBytes",
        "Verbatim_MemConsStmtsLengths",
        "Analytics_MissingJumpTarget",
        "Analytics_NonModeledMLOAD",
        "Verbatim_KnownAndAllLoads",
        "MemWriteToMemConsStmtInfo",
        "StaticallyGuardedBlock",
        "Verbatim_AllVsModeledMLOADs",
        "bytecode",
        "Analytics_ERC20TransferCall",
        "IRFunctionCall",
        "Analytics_FunctionCallWithReturn",
        "Analytics_PolymorphicTarget",
        "CallToSignature",
        "TAC_Use",
        "StorageVariableType",
        "inliner",
        "InFunction",
        "Analytics_JumpToMany",
        "IsKnownLoad",
        "EventSignatureInContract",
        "ConstantPossibleSigHash",
        "TAC_Block_Head",
        "Verbatim_KnownAndAllStores",
        "TAC_Statement_Next",
        "Analytics_ReachableBlocksInTAC",
        "ActualReturnArgs",
        "Analytics_Functions",
        "StatementWritesMemoryOfConstantLengthAtMemAlias",
        "SenderGuard",
        "MSTOREToMemConsStmt_WrittenVar",
        "IRBlock_Gas",
        "Analytics_BlocksReachableInGlobalButNotInTAC",
        "PHILocation",
        "AllCALLsClassified",
        "Analytics_Blocks",
        "Analytics_ReachableBlocks",
        "TAC_Op",
        "LowBytesMaskOp",
        "HighLevelFunctionName",
        "ControlsWith",
        "MemWriteToMemConsStmtInfoInit",
        "Analytics_BlockIsEmpty",
        "VulnerabilityDescription_WalletGriefing",
        "LocalBlockEdge",
        "ArrayWriteToRelativeIndex",
        "IRFunctionEntry",
        "Dominates",
        "Function",
        "Analytics_PublicFunctionNameResolved",
        "VarHoldsBytesOfStorVarFinal",
        "PublicFunctionArg",
        "TAC_Var",
        "inliner",
        "MemWriteToMemConsStmtResolved",
        "ArrayActualArg",
        "Analytics_JumpToManyWithoutGlobalImprecision",
        "Verbatim_AllVsModeledMSTOREs",
        "inliner",
        "MemWriteToMemConsStmtLowerLimit",
        "Analytics_PublicFunctionArg",
        "Verbatim_CDLAllVSStaticVSArr",
        "inliner",
        "Statement_IRStatement",
        "PublicFunction",
        "AntiMaskOp",
        "VulnerabilityDescription_OverflowLoopIterator",
        "Analytics_UnreachableBlock",
        "MemWriteToMemConsStmtInvalid",
        "IRFunctionCallReturn",
        "inliner",
        "VarWrittenToBytesOfStorVarFinal",
        "IRBlockEdge",
        "inliner",
        "TAC_Stmt"
      ],
      [],
      {
        "disassemble_time": 0.05769634246826172,
        "decomp_time": 1.95849609375,
        "inline_time": 0.8381848335266113,
        "client_time": 0.14530563354492188,
        "Analytics_ERC20ApproveCall": 0,
        "Analytics_MemConsStmtUsesFromDistinctPaths": 8,
        "Analytics_FunctionCall": 108,
        "Analytics_MissingImplementation": 0,
        "Analytics_PublicFunction": 29,
        "Analytics_Jumps": 379,
        "Analytics_CallWithSig": 3,
        "Analytics_PublicFunctionArrayArg": 1,
        "Analytics_StmtMissingOperand": 0,
        "Analytics_BlockInNoFunctions": 0,
        "Analytics_DeadBlocks": 0,
        "Analytics_FunctionWithMultipleReturns": 1,
        "Analytics_NonModeledMSTORE": 31,
        "Analytics_BlockInMultipleFunctions": 0,
        "Analytics_InexactFunctionCallArguments": 0,
        "Analytics_MissingJumpTarget": 6,
        "Analytics_NonModeledMLOAD": 34,
        "Analytics_ERC20TransferCall": 2,
        "Analytics_FunctionCallWithReturn": 80,
        "Analytics_PolymorphicTarget": 2,
        "Analytics_InitiallyMissedCycleEntry": 0,
        "Analytics_JumpToMany": 1,
        "Analytics_JumpToManyNonPopBlock": 0,
        "Analytics_InexactFunctionArguments": 0,
        "Analytics_DoubleDef": 0,
        "Analytics_ReachableBlocksInTAC": 478,
        "Analytics_Functions": 61,
        "Analytics_BlocksLocalOrNot": 0,
        "Analytics_BlocksReachableInGlobalButNotInTAC": 4,
        "Analytics_BlockHasNoIRBlock": 0,
        "Analytics_Blocks": 594,
        "Analytics_ReachableBlocks": 482,
        "Analytics_BlockIsEmpty": 11,
        "Analytics_PublicFunctionNameResolved": 19,
        "Analytics_ERC20TransferFromCall": 0,
        "Analytics_UnknownOperand": 0,
        "Analytics_JumpToManyWithoutGlobalImprecision": 1,
        "Analytics_LenVarHasManyVars": 0,
        "Analytics_PublicFunctionArg": 30,
        "Analytics_InexactFunctionReturnArguments": 0,
        "Analytics_UnreachableBlock": 22,
        "Analytics_PolymorphicTargetSameCtx": 0,
        "Verbatim_MemConsStmtsLengths": "185\t170\t170\n",
        "Verbatim_KnownAndAllLoads": "90\t107\n",
        "Verbatim_AllVsModeledMLOADs": "228\t150\t2\t20\t0\t22\n",
        "Verbatim_KnownAndAllStores": "27\t50\n",
        "Verbatim_AllVsModeledMSTOREs": "362\t21\t0\t38\t47\t251\n",
        "Verbatim_CDLAllVSStaticVSArr": "31\t30\t1\n",
        "UnboundedMassOp": "",
        "WalletGriefing": "",
        "OverflowLoopIterator": ""
      }
    ]
  ]
}