{
  "contract": "../data/dataset/eth2/0xD3cb32B1B45916ffdf738810f6bC822fC6A68919.hex",
  "tool": "securify",
  "start": 1659435703.520795,
  "end": 1659435706.5767856,
  "exit_code": 0,
  "duration": 3.05599045753479,
  "success": true,
  "findings": [],
  "errors": [],
  "analysis": {
    "../data/dataset/eth2/0xD3cb32B1B45916ffdf738810f6bC822fC6A68919.hex:0xD3cb32B1B45916ffdf738810f6bC822fC6A68919": {
      "results": {
        "DAO": {
          "completed": true,
          "hasViolations": false,
          "hasWarnings": false,
          "hasSafe": false,
          "hasConflicts": false,
          "violations": [],
          "warnings": [],
          "safe": [],
          "conflicts": []
        },
        "DAOConstantGas": {
          "completed": true,
          "hasViolations": false,
          "hasWarnings": false,
          "hasSafe": false,
          "hasConflicts": false,
          "violations": [],
          "warnings": [],
          "safe": [],
          "conflicts": []
        },
        "MissingInputValidation": {
          "completed": true,
          "error": "not supported",
          "hasViolations": false,
          "hasWarnings": false,
          "hasSafe": false,
          "hasConflicts": false,
          "violations": [],
          "warnings": [],
          "safe": [],
          "conflicts": []
        },
        "TODAmount": {
          "completed": true,
          "hasViolations": false,
          "hasWarnings": false,
          "hasSafe": false,
          "hasConflicts": false,
          "violations": [],
          "warnings": [],
          "safe": [],
          "conflicts": []
        },
        "TODReceiver": {
          "completed": true,
          "hasViolations": false,
          "hasWarnings": false,
          "hasSafe": false,
          "hasConflicts": false,
          "violations": [],
          "warnings": [],
          "safe": [],
          "conflicts": []
        },
        "TODTransfer": {
          "completed": true,
          "hasViolations": false,
          "hasWarnings": false,
          "hasSafe": false,
          "hasConflicts": false,
          "violations": [],
          "warnings": [],
          "safe": [],
          "conflicts": []
        },
        "UnhandledException": {
          "completed": true,
          "hasViolations": false,
          "hasWarnings": false,
          "hasSafe": false,
          "hasConflicts": false,
          "violations": [],
          "warnings": [],
          "safe": [],
          "conflicts": []
        },
        "UnrestrictedEtherFlow": {
          "completed": true,
          "hasViolations": false,
          "hasWarnings": false,
          "hasSafe": false,
          "hasConflicts": false,
          "violations": [],
          "warnings": [],
          "safe": [],
          "conflicts": []
        }
      }
    }
  }
}